dissect/vmfs/__init__.py
dissect/vmfs/address.py
dissect/vmfs/c_lvm.py
dissect/vmfs/c_lvm.pyi
dissect/vmfs/c_vmfs.py
dissect/vmfs/c_vmfs.pyi
dissect/vmfs/descriptor.py
dissect/vmfs/exception.py
dissect/vmfs/lvm.py
dissect/vmfs/resource.py
dissect/vmfs/util.py
dissect/vmfs/vmfs.py
dissect_vmfs-3.12.dist-info/licenses/COPYRIGHT
dissect_vmfs-3.12.dist-info/licenses/LICENSE
dissect_vmfs-3.12.dist-info/METADATA
dissect_vmfs-3.12.dist-info/WHEEL
dissect_vmfs-3.12.dist-info/top_level.txt
dissect_vmfs-3.12.dist-info/RECORD
